genestore-0.11.0.dist-info/METADATA
genestore-0.11.0.dist-info/WHEEL
genestore-0.11.0.dist-info/licenses/LICENSE
genestore/__init__.py
genestore/genestore.cpython-312-x86_64-linux-gnu.so
genestore-0.11.0.dist-info/RECORD
